odoo10_addon_sales_team_operating_unit-10.0.1.0.0.99.dev4-py2.7-nspkg.pth
odoo/addons/sales_team_operating_unit/README.rst
odoo/addons/sales_team_operating_unit/__init__.py
odoo/addons/sales_team_operating_unit/__manifest__.py
odoo/addons/sales_team_operating_unit/models/__init__.py
odoo/addons/sales_team_operating_unit/models/crm_team.py
odoo/addons/sales_team_operating_unit/security/crm_security.xml
odoo/addons/sales_team_operating_unit/static/description/icon.png
odoo/addons/sales_team_operating_unit/tests/__init__.py
odoo/addons/sales_team_operating_unit/tests/test_crm_team_operating_unit.py
odoo/addons/sales_team_operating_unit/views/crm_team_view.xml
odoo10_addon_sales_team_operating_unit-10.0.1.0.0.99.dev4.dist-info/METADATA
odoo10_addon_sales_team_operating_unit-10.0.1.0.0.99.dev4.dist-info/RECORD
odoo10_addon_sales_team_operating_unit-10.0.1.0.0.99.dev4.dist-info/WHEEL
odoo10_addon_sales_team_operating_unit-10.0.1.0.0.99.dev4.dist-info/namespace_packages.txt
odoo10_addon_sales_team_operating_unit-10.0.1.0.0.99.dev4.dist-info/top_level.txt
